<annotation>
	<folder>red_ball</folder>
	<filename>dodgeballs.jpg</filename>
	<path>C:\Users\sem.onyalo\Downloads\_ml_images\red_ball\dodgeballs.jpg</path>
	<source>
		<database>Unknown</database>
	</source>
	<size>
		<width>615</width>
		<height>461</height>
		<depth>3</depth>
	</size>
	<segmented>0</segmented>
	<object>
		<name>red ball</name>
		<pose>Unspecified</pose>
		<truncated>0</truncated>
		<difficult>0</difficult>
		<bndbox>
			<xmin>25</xmin>
			<ymin>125</ymin>
			<xmax>274</xmax>
			<ymax>364</ymax>
		</bndbox>
	</object>
</annotation>
